dataset_image_converter/SONY_ILCE-7RM4_iso100_FE_70_200mm_F2.8_GM_OSS_f5.6_daylight.dcp
dataset_image_converter/__init__.py
dataset_image_converter/__main__.py
dataset_image_converter/conf.py
dataset_image_converter/convert.py
dataset_image_converter/jobs.py
dataset_image_converter/lambda.py
dataset_image_converter/object_storage.py
dataset_image_converter/storages/__init__.py
dataset_image_converter/storages/containers.py
dataset_image_converter/storages/fs.py
dataset_image_converter-0.2.0.dist-info/AUTHORS.rst
dataset_image_converter-0.2.0.dist-info/LICENSE
dataset_image_converter-0.2.0.dist-info/METADATA
dataset_image_converter-0.2.0.dist-info/WHEEL
dataset_image_converter-0.2.0.dist-info/top_level.txt
dataset_image_converter-0.2.0.dist-info/RECORD
