Metadata-Version: 2.2
Name: dataset-image-converter
Version: 0.2.0
Summary: Image dataset format benchmark
Home-page: https://github.com/kamikaze/dataset-image-converter
Author: Oleg Korsak
Author-email: kamikaze.is.waiting.you@gmail.com
License: gpl-3
Project-URL: Documentation, https://github.com/kamikaze/dataset-image-converter/wiki
Platform: any
Classifier: Development Status :: 4 - Beta
Classifier: Programming Language :: Python
Requires-Python: >=3.13
License-File: LICENSE
License-File: AUTHORS.rst
Requires-Dist: aiobotocore==2.19.0
Requires-Dist: colour-science==0.4.6
Requires-Dist: Cython==3.0.11
Requires-Dist: exif==1.6.1
Requires-Dist: h5py==3.12.1
Requires-Dist: imageio[freeimage,pillow]==2.37.0
Requires-Dist: numpy==2.2.2
Requires-Dist: pkgconfig==1.5.5
Requires-Dist: python3-commons==0.6.5
Requires-Dist: rawpy==0.24.0
Requires-Dist: tifffile[all]==2025.1.10
Requires-Dist: types-aiobotocore[s3]==2.19.0
Requires-Dist: zarr<3.0.0
